[
  {
    "source": "Mental Health & Emotional Wellbeing",
    "target": "Lifestyle, Diet & Supplements",
    "weight": 3
  },
  {
    "source": "Mental Health & Emotional Wellbeing",
    "target": "Metabolic & Endocrine Disorders",
    "weight": 1
  },
  {
    "source": "Mental Health & Emotional Wellbeing",
    "target": "Cancer & Oncology",
    "weight": 2
  },
  {
    "source": "Mental Health & Emotional Wellbeing",
    "target": "Respiratory Conditions & Treatments",
    "weight": 1
  },
  {
    "source": "Mental Health & Emotional Wellbeing",
    "target": "Reproductive & Sexual Health (Women's Health & Men's Health)",
    "weight": 1
  },
  {
    "source": "Mental Health & Emotional Wellbeing",
    "target": "Pain & Musculoskeletal Conditions",
    "weight": 1
  },
  {
    "source": "Lifestyle, Diet & Supplements",
    "target": "Metabolic & Endocrine Disorders",
    "weight": 1
  },
  {
    "source": "Lifestyle, Diet & Supplements",
    "target": "Substance Abuse & Addiction",
    "weight": 1
  },
  {
    "source": "Lifestyle, Diet & Supplements",
    "target": "Respiratory Conditions & Treatments",
    "weight": 4
  },
  {
    "source": "Lifestyle, Diet & Supplements",
    "target": "Cancer & Oncology",
    "weight": 14
  },
  {
    "source": "Lifestyle, Diet & Supplements",
    "target": "Neurological Disorders",
    "weight": 1
  },
  {
    "source": "Lifestyle, Diet & Supplements",
    "target": "Medications & Treatment Monitoring",
    "weight": 1
  },
  {
    "source": "Lifestyle, Diet & Supplements",
    "target": "Dermatology & Skin-Related",
    "weight": 1
  },
  {
    "source": "Lifestyle, Diet & Supplements",
    "target": "Procedures, Surgeries & Medical Devices",
    "weight": 3
  },
  {
    "source": "Lifestyle, Diet & Supplements",
    "target": "Reproductive & Sexual Health (Women's Health & Men's Health)",
    "weight": 6
  },
  {
    "source": "Lifestyle, Diet & Supplements",
    "target": "Hematology & Blood Disorders",
    "weight": 1
  },
  {
    "source": "Lifestyle, Diet & Supplements",
    "target": "Pain & Musculoskeletal Conditions",
    "weight": 4
  },
  {
    "source": "Metabolic & Endocrine Disorders",
    "target": "Cancer & Oncology",
    "weight": 1
  },
  {
    "source": "Metabolic & Endocrine Disorders",
    "target": "Respiratory Conditions & Treatments",
    "weight": 1
  },
  {
    "source": "Metabolic & Endocrine Disorders",
    "target": "Pain & Musculoskeletal Conditions",
    "weight": 1
  },
  {
    "source": "Substance Abuse & Addiction",
    "target": "Dermatology & Skin-Related",
    "weight": 1
  },
  {
    "source": "Substance Abuse & Addiction",
    "target": "Cancer & Oncology",
    "weight": 1
  },
  {
    "source": "Respiratory Conditions & Treatments",
    "target": "Cancer & Oncology",
    "weight": 6
  },
  {
    "source": "Respiratory Conditions & Treatments",
    "target": "Procedures, Surgeries & Medical Devices",
    "weight": 1
  },
  {
    "source": "Respiratory Conditions & Treatments",
    "target": "Reproductive & Sexual Health (Women's Health & Men's Health)",
    "weight": 1
  },
  {
    "source": "Respiratory Conditions & Treatments",
    "target": "Pain & Musculoskeletal Conditions",
    "weight": 2
  },
  {
    "source": "Cancer & Oncology",
    "target": "Neurological Disorders",
    "weight": 2
  },
  {
    "source": "Cancer & Oncology",
    "target": "Medications & Treatment Monitoring",
    "weight": 1
  },
  {
    "source": "Cancer & Oncology",
    "target": "Dermatology & Skin-Related",
    "weight": 1
  },
  {
    "source": "Cancer & Oncology",
    "target": "Procedures, Surgeries & Medical Devices",
    "weight": 7
  },
  {
    "source": "Cancer & Oncology",
    "target": "Reproductive & Sexual Health (Women's Health & Men's Health)",
    "weight": 4
  },
  {
    "source": "Cancer & Oncology",
    "target": "Hematology & Blood Disorders",
    "weight": 1
  },
  {
    "source": "Cancer & Oncology",
    "target": "Pain & Musculoskeletal Conditions",
    "weight": 7
  },
  {
    "source": "Cancer & Oncology",
    "target": "Autoimmune Diseases",
    "weight": 1
  },
  {
    "source": "Neurological Disorders",
    "target": "Pain & Musculoskeletal Conditions",
    "weight": 1
  },
  {
    "source": "Neurological Disorders",
    "target": "Procedures, Surgeries & Medical Devices",
    "weight": 2
  },
  {
    "source": "Medications & Treatment Monitoring",
    "target": "Hematology & Blood Disorders",
    "weight": 1
  },
  {
    "source": "Medications & Treatment Monitoring",
    "target": "Reproductive & Sexual Health (Women's Health & Men's Health)",
    "weight": 1
  },
  {
    "source": "Procedures, Surgeries & Medical Devices",
    "target": "Reproductive & Sexual Health (Women's Health & Men's Health)",
    "weight": 1
  },
  {
    "source": "Procedures, Surgeries & Medical Devices",
    "target": "Pain & Musculoskeletal Conditions",
    "weight": 3
  },
  {
    "source": "Procedures, Surgeries & Medical Devices",
    "target": "Autoimmune Diseases",
    "weight": 1
  },
  {
    "source": "Reproductive & Sexual Health (Women's Health & Men's Health)",
    "target": "Hematology & Blood Disorders",
    "weight": 1
  },
  {
    "source": "Reproductive & Sexual Health (Women's Health & Men's Health)",
    "target": "Pain & Musculoskeletal Conditions",
    "weight": 1
  }
]